
<list>
	<npc>
		<type>49</type>
		<size>2</size>
	</npc>
	<npc>
		<type>50</type>
		<size>5</size>
	</npc>
	<npc>
		<type>51</type>
		<size>2</size>
	</npc>
	<npc>
		<type>52</type>
		<size>2</size>
	</npc>
	<npc>
		<type>53</type>
		<size>4</size>
	</npc>
	<npc>
		<type>54</type>
		<size>4</size>
	</npc>
	<npc>
		<type>55</type>
		<size>4</size>
	</npc>
	<npc>
		<type>69</type>
		<size>2</size>
	</npc>
	<npc>
		<type>78</type>
		<size>2</size>
	</npc>
	<npc>
		<type>79</type>
		<size>2</size>
	</npc>
	<npc>
		<type>80</type>
		<size>2</size>
	</npc>
	<npc>
		<type>81</type>
		<size>2</size>
	</npc>
	<npc>
		<type>82</type>
		<size>2</size>
	</npc>
	<npc>
		<type>83</type>
		<size>3</size>
	</npc>
	<npc>
		<type>84</type>
		<size>3</size>
	</npc>
	<npc>
		<type>85</type>
		<size>2</size>
	</npc>
	<npc>
		<type>86</type>
		<size>2</size>
	</npc>
	<npc>
		<type>87</type>
		<size>2</size>
	</npc>
	<npc>
		<type>88</type>
		<size>2</size>
	</npc>
	<npc>
		<type>89</type>
		<size>2</size>
	</npc>
	<npc>
		<type>95</type>
		<size>2</size>
	</npc>
	<npc>
		<type>96</type>
		<size>2</size>
	</npc>
	<npc>
		<type>97</type>
		<size>2</size>
	</npc>
	<npc>
		<type>105</type>
		<size>2</size>
	</npc>
	<npc>
		<type>106</type>
		<size>2</size>
	</npc>
	<npc>
		<type>107</type>
		<size>2</size>
	</npc>
	<npc>
		<type>108</type>
		<size>2</size>
	</npc>
	<npc>
		<type>110</type>
		<size>2</size>
	</npc>
	<npc>
		<type>111</type>
		<size>2</size>
	</npc>
	<npc>
		<type>112</type>
		<size>2</size>
	</npc>
	<npc>
		<type>113</type>
		<size>2</size>
	</npc>
	<npc>
		<type>114</type>
		<size>2</size>
	</npc>
	<npc>
		<type>115</type>
		<size>2</size>
	</npc>
	<npc>
		<type>116</type>
		<size>2</size>
	</npc>
	<npc>
		<type>117</type>
		<size>2</size>
	</npc>
	<npc>
		<type>130</type>
		<size>3</size>
	</npc>
	<npc>
		<type>133</type>
		<size>2</size>
	</npc>
	<npc>
		<type>135</type>
		<size>3</size>
	</npc>
	<npc>
		<type>136</type>
		<size>2</size>
	</npc>
	<npc>
		<type>137</type>
		<size>2</size>
	</npc>
	<npc>
		<type>138</type>
		<size>2</size>
	</npc>
	<npc>
		<type>141</type>
		<size>2</size>
	</npc>
	<npc>
		<type>142</type>
		<size>2</size>
	</npc>
	<npc>
		<type>143</type>
		<size>2</size>
	</npc>
	<npc>
		<type>144</type>
		<size>2</size>
	</npc>
	<npc>
		<type>146</type>
		<size>2</size>
	</npc>
	<npc>
		<type>147</type>
		<size>2</size>
	</npc>
	<npc>
		<type>148</type>
		<size>2</size>
	</npc>
	<npc>
		<type>149</type>
		<size>2</size>
	</npc>
	<npc>
		<type>150</type>
		<size>2</size>
	</npc>
	<npc>
		<type>269</type>
		<size>2</size>
	</npc>
	<npc>
		<type>270</type>
		<size>2</size>
	</npc>
	<npc>
		<type>271</type>
		<size>2</size>
	</npc>
	<npc>
		<type>374</type>
		<size>2</size>
	</npc>
	<npc>
		<type>397</type>
		<size>2</size>
	</npc>
	<npc>
		<type>446</type>
		<size>2</size>
	</npc>
	<npc>
		<type>667</type>
		<size>3</size>
	</npc>
	<npc>
		<type>677</type>
		<size>3</size>
	</npc>
	<npc>
		<type>742</type>
		<size>4</size>
	</npc>
	<npc>
		<type>752</type>
		<size>2</size>
	</npc>
	<npc>
		<type>839</type>
		<size>2</size>
	</npc>
	<npc>
		<type>840</type>
		<size>2</size>
	</npc>
	<npc>
		<type>852</type>
		<size>2</size>
	</npc>
	<npc>
		<type>853</type>
		<size>2</size>
	</npc>
	<npc>
		<type>854</type>
		<size>2</size>
	</npc>
	<npc>
		<type>855</type>
		<size>2</size>
	</npc>
	<npc>
		<type>856</type>
		<size>2</size>
	</npc>
	<npc>
		<type>857</type>
		<size>2</size>
	</npc>
	<npc>
		<type>858</type>
		<size>2</size>
	</npc>
	<npc>
		<type>859</type>
		<size>2</size>
	</npc>
	<npc>
		<type>860</type>
		<size>2</size>
	</npc>
	<npc>
		<type>861</type>
		<size>2</size>
	</npc>
	<npc>
		<type>862</type>
		<size>2</size>
	</npc>
	<npc>
		<type>863</type>
		<size>2</size>
	</npc>
	<npc>
		<type>864</type>
		<size>2</size>
	</npc>
	<npc>
		<type>865</type>
		<size>2</size>
	</npc>
	<npc>
		<type>866</type>
		<size>2</size>
	</npc>
	<npc>
		<type>867</type>
		<size>2</size>
	</npc>
	<npc>
		<type>868</type>
		<size>2</size>
	</npc>
	<npc>
		<type>869</type>
		<size>2</size>
	</npc>
	<npc>
		<type>870</type>
		<size>2</size>
	</npc>
	<npc>
		<type>871</type>
		<size>2</size>
	</npc>
	<npc>
		<type>873</type>
		<size>2</size>
	</npc>
	<npc>
		<type>874</type>
		<size>2</size>
	</npc>
	<npc>
		<type>875</type>
		<size>2</size>
	</npc>
	<npc>
		<type>876</type>
		<size>2</size>
	</npc>
	<npc>
		<type>879</type>
		<size>2</size>
	</npc>
	<npc>
		<type>880</type>
		<size>2</size>
	</npc>
	<npc>
		<type>899</type>
		<size>2</size>
	</npc>
	<npc>
		<type>909</type>
		<size>3</size>
	</npc>
	<npc>
		<type>911</type>
		<size>3</size>
	</npc>
	<npc>
		<type>934</type>
		<size>3</size>
	</npc>
	<npc>
		<type>939</type>
		<size>2</size>
	</npc>
	<npc>
		<type>941</type>
		<size>4</size>
	</npc>
	<npc>
		<type>950</type>
		<size>2</size>
	</npc>
	<npc>
		<type>955</type>
		<size>2</size>
	</npc>
	<npc>
		<type>978</type>
		<size>2</size>
	</npc>
	<npc>
		<type>986</type>
		<size>2</size>
	</npc>
	<npc>
		<type>987</type>
		<size>2</size>
	</npc>
	<npc>
		<type>991</type>
		<size>2</size>
	</npc>
	<npc>
		<type>997</type>
		<size>3</size>
	</npc>
	<npc>
		<type>998</type>
		<size>3</size>
	</npc>
	<npc>
		<type>999</type>
		<size>3</size>
	</npc>
	<npc>
		<type>1000</type>
		<size>3</size>
	</npc>
	<npc>
		<type>1003</type>
		<size>2</size>
	</npc>
	<npc>
		<type>1005</type>
		<size>2</size>
	</npc>
	<npc>
		<type>1010</type>
		<size>2</size>
	</npc>
	<npc>
		<type>1047</type>
		<size>2</size>
	</npc>
	<npc>
		<type>1052</type>
		<size>2</size>
	</npc>
	<npc>
		<type>1053</type>
		<size>2</size>
	</npc>
	<npc>
		<type>1069</type>
		<size>2</size>
	</npc>
	<npc>
		<type>1095</type>
		<size>2</size>
	</npc>
	<npc>
		<type>1096</type>
		<size>2</size>
	</npc>
	<npc>
		<type>1097</type>
		<size>2</size>
	</npc>
	<npc>
		<type>1098</type>
		<size>2</size>
	</npc>
	<npc>
		<type>1099</type>
		<size>2</size>
	</npc>
	<npc>
		<type>1100</type>
		<size>2</size>
	</npc>
	<npc>
		<type>1115</type>
		<size>2</size>
	</npc>
	<npc>
		<type>1116</type>
		<size>2</size>
	</npc>
	<npc>
		<type>1117</type>
		<size>2</size>
	</npc>
	<npc>
		<type>1125</type>
		<size>3</size>
	</npc>
	<npc>
		<type>1126</type>
		<size>2</size>
	</npc>
	<npc>
		<type>1127</type>
		<size>2</size>
	</npc>
	<npc>
		<type>1128</type>
		<size>2</size>
	</npc>
	<npc>
		<type>1129</type>
		<size>2</size>
	</npc>
	<npc>
		<type>1135</type>
		<size>2</size>
	</npc>
	<npc>
		<type>1136</type>
		<size>2</size>
	</npc>
	<npc>
		<type>1137</type>
		<size>2</size>
	</npc>
	<npc>
		<type>1139</type>
		<size>2</size>
	</npc>
	<npc>
		<type>1151</type>
		<size>2</size>
	</npc>
	<npc>
		<type>1153</type>
		<size>2</size>
	</npc>
	<npc>
		<type>1154</type>
		<size>3</size>
	</npc>
	<npc>
		<type>1155</type>
		<size>4</size>
	</npc>
	<npc>
		<type>1156</type>
		<size>2</size>
	</npc>
	<npc>
		<type>1157</type>
		<size>4</size>
	</npc>
	<npc>
		<type>1158</type>
		<size>5</size>
	</npc>
	<npc>
		<type>1159</type>
		<size>5</size>
	</npc>
	<npc>
		<type>1160</type>
		<size>5</size>
	</npc>
	<npc>
		<type>1172</type>
		<size>3</size>
	</npc>
	<npc>
		<type>1173</type>
		<size>3</size>
	</npc>
	<npc>
		<type>1179</type>
		<size>2</size>
	</npc>
	<npc>
		<type>1180</type>
		<size>2</size>
	</npc>
	<npc>
		<type>1181</type>
		<size>2</size>
	</npc>
	<npc>
		<type>1195</type>
		<size>2</size>
	</npc>
	<npc>
		<type>1196</type>
		<size>2</size>
	</npc>
	<npc>
		<type>1197</type>
		<size>2</size>
	</npc>
	<npc>
		<type>1198</type>
		<size>2</size>
	</npc>
	<npc>
		<type>1213</type>
		<size>2</size>
	</npc>
	<npc>
		<type>1222</type>
		<size>2</size>
	</npc>
	<npc>
		<type>1224</type>
		<size>2</size>
	</npc>
	<npc>
		<type>1326</type>
		<size>2</size>
	</npc>
	<npc>
		<type>1328</type>
		<size>2</size>
	</npc>
	<npc>
		<type>1329</type>
		<size>2</size>
	</npc>
	<npc>
		<type>1330</type>
		<size>2</size>
	</npc>
	<npc>
		<type>1335</type>
		<size>2</size>
	</npc>
	<npc>
		<type>1341</type>
		<size>2</size>
	</npc>
	<npc>
		<type>1342</type>
		<size>2</size>
	</npc>
	<npc>
		<type>1343</type>
		<size>2</size>
	</npc>
	<npc>
		<type>1344</type>
		<size>2</size>
	</npc>
	<npc>
		<type>1345</type>
		<size>2</size>
	</npc>
	<npc>
		<type>1346</type>
		<size>2</size>
	</npc>
	<npc>
		<type>1347</type>
		<size>2</size>
	</npc>
	<npc>
		<type>1348</type>
		<size>3</size>
	</npc>
	<npc>
		<type>1349</type>
		<size>3</size>
	</npc>
	<npc>
		<type>1350</type>
		<size>3</size>
	</npc>
	<npc>
		<type>1351</type>
		<size>3</size>
	</npc>
	<npc>
		<type>1352</type>
		<size>3</size>
	</npc>
	<npc>
		<type>1353</type>
		<size>3</size>
	</npc>
	<npc>
		<type>1354</type>
		<size>3</size>
	</npc>
	<npc>
		<type>1355</type>
		<size>3</size>
	</npc>
	<npc>
		<type>1356</type>
		<size>3</size>
	</npc>
	<npc>
		<type>1373</type>
		<size>2</size>
	</npc>
	<npc>
		<type>1431</type>
		<size>2</size>
	</npc>
	<npc>
		<type>1432</type>
		<size>2</size>
	</npc>
	<npc>
		<type>1438</type>
		<size>2</size>
	</npc>
	<npc>
		<type>1459</type>
		<size>2</size>
	</npc>
	<npc>
		<type>1460</type>
		<size>2</size>
	</npc>
	<npc>
		<type>1461</type>
		<size>2</size>
	</npc>
	<npc>
		<type>1462</type>
		<size>2</size>
	</npc>
	<npc>
		<type>1472</type>
		<size>3</size>
	</npc>
	<npc>
		<type>1505</type>
		<size>2</size>
	</npc>
	<npc>
		<type>1506</type>
		<size>2</size>
	</npc>
	<npc>
		<type>1507</type>
		<size>2</size>
	</npc>
	<npc>
		<type>1508</type>
		<size>2</size>
	</npc>
	<npc>
		<type>1509</type>
		<size>2</size>
	</npc>
	<npc>
		<type>1516</type>
		<size>3</size>
	</npc>
	<npc>
		<type>1521</type>
		<size>2</size>
	</npc>
	<npc>
		<type>1522</type>
		<size>2</size>
	</npc>
	<npc>
		<type>1542</type>
		<size>3</size>
	</npc>
	<npc>
		<type>1555</type>
		<size>2</size>
	</npc>
	<npc>
		<type>1556</type>
		<size>2</size>
	</npc>
	<npc>
		<type>1558</type>
		<size>2</size>
	</npc>
	<npc>
		<type>1559</type>
		<size>2</size>
	</npc>
	<npc>
		<type>1575</type>
		<size>2</size>
	</npc>
	<npc>
		<type>1578</type>
		<size>3</size>
	</npc>
	<npc>
		<type>1580</type>
		<size>2</size>
	</npc>
	<npc>
		<type>1581</type>
		<size>2</size>
	</npc>
	<npc>
		<type>1582</type>
		<size>2</size>
	</npc>
	<npc>
		<type>1583</type>
		<size>2</size>
	</npc>
	<npc>
		<type>1584</type>
		<size>2</size>
	</npc>
	<npc>
		<type>1585</type>
		<size>2</size>
	</npc>
	<npc>
		<type>1586</type>
		<size>2</size>
	</npc>
	<npc>
		<type>1587</type>
		<size>2</size>
	</npc>
	<npc>
		<type>1588</type>
		<size>2</size>
	</npc>
	<npc>
		<type>1589</type>
		<size>2</size>
	</npc>
	<npc>
		<type>1590</type>
		<size>4</size>
	</npc>
	<npc>
		<type>1591</type>
		<size>4</size>
	</npc>
	<npc>
		<type>1592</type>
		<size>4</size>
	</npc>
	<npc>
		<type>1600</type>
		<size>2</size>
	</npc>
	<npc>
		<type>1601</type>
		<size>2</size>
	</npc>
	<npc>
		<type>1602</type>
		<size>2</size>
	</npc>
	<npc>
		<type>1603</type>
		<size>2</size>
	</npc>
	<npc>
		<type>1604</type>
		<size>2</size>
	</npc>
	<npc>
		<type>1605</type>
		<size>2</size>
	</npc>
	<npc>
		<type>1606</type>
		<size>2</size>
	</npc>
	<npc>
		<type>1607</type>
		<size>2</size>
	</npc>
	<npc>
		<type>1608</type>
		<size>3</size>
	</npc>
	<npc>
		<type>1609</type>
		<size>3</size>
	</npc>
	<npc>
		<type>1610</type>
		<size>3</size>
	</npc>
	<npc>
		<type>1611</type>
		<size>3</size>
	</npc>
	<npc>
		<type>1612</type>
		<size>2</size>
	</npc>
	<npc>
		<type>1616</type>
		<size>2</size>
	</npc>
	<npc>
		<type>1617</type>
		<size>2</size>
	</npc>
	<npc>
		<type>1618</type>
		<size>2</size>
	</npc>
	<npc>
		<type>1619</type>
		<size>2</size>
	</npc>
	<npc>
		<type>1620</type>
		<size>2</size>
	</npc>
	<npc>
		<type>1621</type>
		<size>3</size>
	</npc>
	<npc>
		<type>1627</type>
		<size>2</size>
	</npc>
	<npc>
		<type>1628</type>
		<size>2</size>
	</npc>
	<npc>
		<type>1631</type>
		<size>2</size>
	</npc>
	<npc>
		<type>1632</type>
		<size>2</size>
	</npc>
	<npc>
		<type>1653</type>
		<size>2</size>
	</npc>
	<npc>
		<type>1654</type>
		<size>2</size>
	</npc>
	<npc>
		<type>1655</type>
		<size>2</size>
	</npc>
	<npc>
		<type>1656</type>
		<size>2</size>
	</npc>
	<npc>
		<type>1657</type>
		<size>2</size>
	</npc>
	<npc>
		<type>1676</type>
		<size>2</size>
	</npc>
	<npc>
		<type>1677</type>
		<size>2</size>
	</npc>
	<npc>
		<type>1681</type>
		<size>2</size>
	</npc>
	<npc>
		<type>1689</type>
		<size>3</size>
	</npc>
	<npc>
		<type>1691</type>
		<size>2</size>
	</npc>
	<npc>
		<type>1693</type>
		<size>2</size>
	</npc>
	<npc>
		<type>1719</type>
		<size>2</size>
	</npc>
	<npc>
		<type>1720</type>
		<size>2</size>
	</npc>
	<npc>
		<type>1721</type>
		<size>2</size>
	</npc>
	<npc>
		<type>1722</type>
		<size>2</size>
	</npc>
	<npc>
		<type>1723</type>
		<size>2</size>
	</npc>
	<npc>
		<type>1728</type>
		<size>2</size>
	</npc>
	<npc>
		<type>1730</type>
		<size>2</size>
	</npc>
	<npc>
		<type>1731</type>
		<size>2</size>
	</npc>
	<npc>
		<type>1732</type>
		<size>2</size>
	</npc>
	<npc>
		<type>1733</type>
		<size>2</size>
	</npc>
	<npc>
		<type>1734</type>
		<size>2</size>
	</npc>
	<npc>
		<type>1735</type>
		<size>2</size>
	</npc>
	<npc>
		<type>1736</type>
		<size>2</size>
	</npc>
	<npc>
		<type>1737</type>
		<size>2</size>
	</npc>
	<npc>
		<type>1738</type>
		<size>2</size>
	</npc>
	<npc>
		<type>1739</type>
		<size>3</size>
	</npc>
	<npc>
		<type>1740</type>
		<size>3</size>
	</npc>
	<npc>
		<type>1741</type>
		<size>2</size>
	</npc>
	<npc>
		<type>1742</type>
		<size>3</size>
	</npc>
	<npc>
		<type>1743</type>
		<size>3</size>
	</npc>
	<npc>
		<type>1744</type>
		<size>3</size>
	</npc>
	<npc>
		<type>1745</type>
		<size>2</size>
	</npc>
	<npc>
		<type>1746</type>
		<size>2</size>
	</npc>
	<npc>
		<type>1747</type>
		<size>3</size>
	</npc>
	<npc>
		<type>1748</type>
		<size>3</size>
	</npc>
	<npc>
		<type>1750</type>
		<size>2</size>
	</npc>
	<npc>
		<type>1766</type>
		<size>2</size>
	</npc>
	<npc>
		<type>1767</type>
		<size>2</size>
	</npc>
	<npc>
		<type>1768</type>
		<size>2</size>
	</npc>
	<npc>
		<type>1778</type>
		<size>2</size>
	</npc>
	<npc>
		<type>1779</type>
		<size>2</size>
	</npc>
	<npc>
		<type>1780</type>
		<size>2</size>
	</npc>
	<npc>
		<type>1781</type>
		<size>2</size>
	</npc>
	<npc>
		<type>1782</type>
		<size>2</size>
	</npc>
	<npc>
		<type>1783</type>
		<size>2</size>
	</npc>
	<npc>
		<type>1784</type>
		<size>2</size>
	</npc>
	<npc>
		<type>1785</type>
		<size>2</size>
	</npc>
	<npc>
		<type>1786</type>
		<size>2</size>
	</npc>
	<npc>
		<type>1787</type>
		<size>2</size>
	</npc>
	<npc>
		<type>1792</type>
		<size>2</size>
	</npc>
	<npc>
		<type>1802</type>
		<size>2</size>
	</npc>
	<npc>
		<type>1803</type>
		<size>2</size>
	</npc>
	<npc>
		<type>1804</type>
		<size>2</size>
	</npc>
	<npc>
		<type>1811</type>
		<size>2</size>
	</npc>
	<npc>
		<type>1812</type>
		<size>2</size>
	</npc>
	<npc>
		<type>1813</type>
		<size>2</size>
	</npc>
	<npc>
		<type>1821</type>
		<size>2</size>
	</npc>
	<npc>
		<type>1828</type>
		<size>2</size>
	</npc>
	<npc>
		<type>1873</type>
		<size>2</size>
	</npc>
	<npc>
		<type>1943</type>
		<size>2</size>
	</npc>
	<npc>
		<type>1944</type>
		<size>2</size>
	</npc>
	<npc>
		<type>1945</type>
		<size>2</size>
	</npc>
	<npc>
		<type>1946</type>
		<size>2</size>
	</npc>
	<npc>
		<type>1951</type>
		<size>2</size>
	</npc>
	<npc>
		<type>1952</type>
		<size>2</size>
	</npc>
	<npc>
		<type>1953</type>
		<size>2</size>
	</npc>
	<npc>
		<type>1954</type>
		<size>2</size>
	</npc>
	<npc>
		<type>1955</type>
		<size>2</size>
	</npc>
	<npc>
		<type>1956</type>
		<size>2</size>
	</npc>
	<npc>
		<type>1970</type>
		<size>2</size>
	</npc>
	<npc>
		<type>1971</type>
		<size>2</size>
	</npc>
	<npc>
		<type>1990</type>
		<size>2</size>
	</npc>
	<npc>
		<type>1993</type>
		<size>2</size>
	</npc>
	<npc>
		<type>1996</type>
		<size>2</size>
	</npc>
	<npc>
		<type>1998</type>
		<size>2</size>
	</npc>
	<npc>
		<type>1999</type>
		<size>2</size>
	</npc>
	<npc>
		<type>2000</type>
		<size>2</size>
	</npc>
	<npc>
		<type>2022</type>
		<size>3</size>
	</npc>
	<npc>
		<type>2033</type>
		<size>2</size>
	</npc>
	<npc>
		<type>2038</type>
		<size>2</size>
	</npc>
	<npc>
		<type>2039</type>
		<size>2</size>
	</npc>
	<npc>
		<type>2040</type>
		<size>2</size>
	</npc>
	<npc>
		<type>2041</type>
		<size>2</size>
	</npc>
	<npc>
		<type>2042</type>
		<size>2</size>
	</npc>
	<npc>
		<type>2043</type>
		<size>2</size>
	</npc>
	<npc>
		<type>2044</type>
		<size>2</size>
	</npc>
	<npc>
		<type>2045</type>
		<size>2</size>
	</npc>
	<npc>
		<type>2046</type>
		<size>2</size>
	</npc>
	<npc>
		<type>2047</type>
		<size>2</size>
	</npc>
	<npc>
		<type>2048</type>
		<size>2</size>
	</npc>
	<npc>
		<type>2049</type>
		<size>2</size>
	</npc>
	<npc>
		<type>2050</type>
		<size>2</size>
	</npc>
	<npc>
		<type>2051</type>
		<size>2</size>
	</npc>
	<npc>
		<type>2052</type>
		<size>2</size>
	</npc>
	<npc>
		<type>2053</type>
		<size>2</size>
	</npc>
	<npc>
		<type>2054</type>
		<size>2</size>
	</npc>
	<npc>
		<type>2055</type>
		<size>2</size>
	</npc>
	<npc>
		<type>2056</type>
		<size>2</size>
	</npc>
	<npc>
		<type>2057</type>
		<size>2</size>
	</npc>
	<npc>
		<type>2060</type>
		<size>3</size>
	</npc>
	<npc>
		<type>2063</type>
		<size>2</size>
	</npc>
	<npc>
		<type>2064</type>
		<size>2</size>
	</npc>
	<npc>
		<type>2065</type>
		<size>2</size>
	</npc>
	<npc>
		<type>2240</type>
		<size>2</size>
	</npc>
	<npc>
		<type>2252</type>
		<size>2</size>
	</npc>
	<npc>
		<type>2254</type>
		<size>2</size>
	</npc>
	<npc>
		<type>2255</type>
		<size>2</size>
	</npc>
	<npc>
		<type>2289</type>
		<size>2</size>
	</npc>
	<npc>
		<type>2317</type>
		<size>2</size>
	</npc>
	<npc>
		<type>2417</type>
		<size>2</size>
	</npc>
	<npc>
		<type>2418</type>
		<size>2</size>
	</npc>
	<npc>
		<type>2419</type>
		<size>2</size>
	</npc>
	<npc>
		<type>2434</type>
		<size>2</size>
	</npc>
	<npc>
		<type>2452</type>
		<size>2</size>
	</npc>
	<npc>
		<type>2453</type>
		<size>2</size>
	</npc>
	<npc>
		<type>2482</type>
		<size>2</size>
	</npc>
	<npc>
		<type>2534</type>
		<size>3</size>
	</npc>
	<npc>
		<type>2554</type>
		<size>3</size>
	</npc>
	<npc>
		<type>2555</type>
		<size>3</size>
	</npc>
	<npc>
		<type>2556</type>
		<size>3</size>
	</npc>
	<npc>
		<type>2557</type>
		<size>3</size>
	</npc>
	<npc>
		<type>2558</type>
		<size>3</size>
	</npc>
	<npc>
		<type>2559</type>
		<size>3</size>
	</npc>
	<npc>
		<type>2560</type>
		<size>3</size>
	</npc>
	<npc>
		<type>2561</type>
		<size>3</size>
	</npc>
	<npc>
		<type>2562</type>
		<size>3</size>
	</npc>
	<npc>
		<type>2563</type>
		<size>3</size>
	</npc>
	<npc>
		<type>2629</type>
		<size>2</size>
	</npc>
	<npc>
		<type>2630</type>
		<size>2</size>
	</npc>
	<npc>
		<type>2631</type>
		<size>3</size>
	</npc>
	<npc>
		<type>2632</type>
		<size>3</size>
	</npc>
	<npc>
		<type>2637</type>
		<size>2</size>
	</npc>
	<npc>
		<type>2640</type>
		<size>2</size>
	</npc>
	<npc>
		<type>2641</type>
		<size>3</size>
	</npc>
	<npc>
		<type>2642</type>
		<size>5</size>
	</npc>
	<npc>
		<type>2644</type>
		<size>2</size>
	</npc>
	<npc>
		<type>2651</type>
		<size>2</size>
	</npc>
	<npc>
		<type>2722</type>
		<size>2</size>
	</npc>
	<npc>
		<type>2723</type>
		<size>2</size>
	</npc>
	<npc>
		<type>2736</type>
		<size>2</size>
	</npc>
	<npc>
		<type>2737</type>
		<size>2</size>
	</npc>
	<npc>
		<type>2739</type>
		<size>3</size>
	</npc>
	<npc>
		<type>2740</type>
		<size>3</size>
	</npc>
	<npc>
		<type>2741</type>
		<size>4</size>
	</npc>
	<npc>
		<type>2742</type>
		<size>4</size>
	</npc>
	<npc>
		<type>2743</type>
		<size>5</size>
	</npc>
	<npc>
		<type>2744</type>
		<size>5</size>
	</npc>
	<npc>
		<type>2745</type>
		<size>5</size>
	</npc>
	<npc>
		<type>2783</type>
		<size>3</size>
	</npc>
	<npc>
		<type>2801</type>
		<size>2</size>
	</npc>
	<npc>
		<type>2803</type>
		<size>3</size>
	</npc>
	<npc>
		<type>2804</type>
		<size>2</size>
	</npc>
	<npc>
		<type>2805</type>
		<size>2</size>
	</npc>
	<npc>
		<type>2806</type>
		<size>2</size>
	</npc>
	<npc>
		<type>2809</type>
		<size>2</size>
	</npc>
	<npc>
		<type>2810</type>
		<size>2</size>
	</npc>
	<npc>
		<type>2811</type>
		<size>2</size>
	</npc>
	<npc>
		<type>2812</type>
		<size>2</size>
	</npc>
	<npc>
		<type>2813</type>
		<size>2</size>
	</npc>
	<npc>
		<type>2814</type>
		<size>2</size>
	</npc>
	<npc>
		<type>2815</type>
		<size>2</size>
	</npc>
	<npc>
		<type>2849</type>
		<size>2</size>
	</npc>
	<npc>
		<type>2850</type>
		<size>2</size>
	</npc>
	<npc>
		<type>2880</type>
		<size>2</size>
	</npc>
	<npc>
		<type>2881</type>
		<size>3</size>
	</npc>
	<npc>
		<type>2882</type>
		<size>3</size>
	</npc>
	<npc>
		<type>2883</type>
		<size>3</size>
	</npc>
	<npc>
		<type>2885</type>
		<size>2</size>
	</npc>
	<npc>
		<type>2886</type>
		<size>2</size>
	</npc>
	<npc>
		<type>2889</type>
		<size>2</size>
	</npc>
	<npc>
		<type>2890</type>
		<size>2</size>
	</npc>
	<npc>
		<type>2919</type>
		<size>3</size>
	</npc>
	<npc>
		<type>2920</type>
		<size>3</size>
	</npc>
	<npc>
		<type>2921</type>
		<size>3</size>
	</npc>
	<npc>
		<type>3051</type>
		<size>2</size>
	</npc>
	<npc>
		<type>3052</type>
		<size>2</size>
	</npc>
	<npc>
		<type>3053</type>
		<size>2</size>
	</npc>
	<npc>
		<type>3054</type>
		<size>2</size>
	</npc>
	<npc>
		<type>3055</type>
		<size>2</size>
	</npc>
	<npc>
		<type>3056</type>
		<size>2</size>
	</npc>
	<npc>
		<type>3058</type>
		<size>2</size>
	</npc>
	<npc>
		<type>3063</type>
		<size>2</size>
	</npc>
	<npc>
		<type>3064</type>
		<size>2</size>
	</npc>
	<npc>
		<type>3066</type>
		<size>2</size>
	</npc>
	<npc>
		<type>3068</type>
		<size>3</size>
	</npc>
	<npc>
		<type>3069</type>
		<size>3</size>
	</npc>
	<npc>
		<type>3070</type>
		<size>3</size>
	</npc>
	<npc>
		<type>3071</type>
		<size>3</size>
	</npc>
	<npc>
		<type>3072</type>
		<size>2</size>
	</npc>
	<npc>
		<type>3076</type>
		<size>2</size>
	</npc>
	<npc>
		<type>3077</type>
		<size>2</size>
	</npc>
	<npc>
		<type>3100</type>
		<size>2</size>
	</npc>
	<npc>
		<type>3101</type>
		<size>2</size>
	</npc>
	<npc>
		<type>3103</type>
		<size>2</size>
	</npc>
	<npc>
		<type>3124</type>
		<size>2</size>
	</npc>
	<npc>
		<type>3125</type>
		<size>2</size>
	</npc>
	<npc>
		<type>3129</type>
		<size>2</size>
	</npc>
	<npc>
		<type>3130</type>
		<size>2</size>
	</npc>
	<npc>
		<type>3132</type>
		<size>2</size>
	</npc>
	<npc>
		<type>3133</type>
		<size>2</size>
	</npc>
	<npc>
		<type>3134</type>
		<size>2</size>
	</npc>
	<npc>
		<type>3135</type>
		<size>2</size>
	</npc>
	<npc>
		<type>3140</type>
		<size>3</size>
	</npc>
	<npc>
		<type>3154</type>
		<size>2</size>
	</npc>
	<npc>
		<type>3200</type>
		<size>3</size>
	</npc>
	<npc>
		<type>3203</type>
		<size>3</size>
	</npc>
	<npc>
		<type>3301</type>
		<size>3</size>
	</npc>
	<npc>
		<type>3309</type>
		<size>2</size>
	</npc>
	<npc>
		<type>3332</type>
		<size>5</size>
	</npc>
	<npc>
		<type>3333</type>
		<size>5</size>
	</npc>
	<npc>
		<type>3334</type>
		<size>5</size>
	</npc>
	<npc>
		<type>3337</type>
		<size>3</size>
	</npc>
	<npc>
		<type>3338</type>
		<size>3</size>
	</npc>
	<npc>
		<type>3339</type>
		<size>4</size>
	</npc>
	<npc>
		<type>3340</type>
		<size>3</size>
	</npc>
	<npc>
		<type>3347</type>
		<size>2</size>
	</npc>
	<npc>
		<type>3376</type>
		<size>2</size>
	</npc>
	<npc>
		<type>3398</type>
		<size>2</size>
	</npc>
	<npc>
		<type>3419</type>
		<size>2</size>
	</npc>
	<npc>
		<type>3420</type>
		<size>2</size>
	</npc>
	<npc>
		<type>3421</type>
		<size>2</size>
	</npc>
	<npc>
		<type>3423</type>
		<size>2</size>
	</npc>
	<npc>
		<type>3443</type>
		<size>2</size>
	</npc>
	<npc>
		<type>3444</type>
		<size>2</size>
	</npc>
	<npc>
		<type>3445</type>
		<size>3</size>
	</npc>
	<npc>
		<type>3446</type>
		<size>2</size>
	</npc>
	<npc>
		<type>3447</type>
		<size>2</size>
	</npc>
	<npc>
		<type>3448</type>
		<size>3</size>
	</npc>
	<npc>
		<type>3463</type>
		<size>2</size>
	</npc>
	<npc>
		<type>3464</type>
		<size>2</size>
	</npc>
	<npc>
		<type>3466</type>
		<size>2</size>
	</npc>
	<npc>
		<type>3467</type>
		<size>2</size>
	</npc>
	<npc>
		<type>3468</type>
		<size>2</size>
	</npc>
	<npc>
		<type>3469</type>
		<size>5</size>
	</npc>
	<npc>
		<type>3470</type>
		<size>5</size>
	</npc>
	<npc>
		<type>3471</type>
		<size>5</size>
	</npc>
	<npc>
		<type>3472</type>
		<size>5</size>
	</npc>
	<npc>
		<type>3476</type>
		<size>3</size>
	</npc>
	<npc>
		<type>3477</type>
		<size>3</size>
	</npc>
	<npc>
		<type>3484</type>
		<size>2</size>
	</npc>
	<npc>
		<type>3493</type>
		<size>3</size>
	</npc>
	<npc>
		<type>3494</type>
		<size>5</size>
	</npc>
	<npc>
		<type>3497</type>
		<size>3</size>
	</npc>
	<npc>
		<type>3498</type>
		<size>3</size>
	</npc>
	<npc>
		<type>3499</type>
		<size>3</size>
	</npc>
	<npc>
		<type>3500</type>
		<size>3</size>
	</npc>
	<npc>
		<type>3501</type>
		<size>3</size>
	</npc>
	<npc>
		<type>3502</type>
		<size>3</size>
	</npc>
	<npc>
		<type>3519</type>
		<size>2</size>
	</npc>
	<npc>
		<type>3530</type>
		<size>3</size>
	</npc>
	<npc>
		<type>3556</type>
		<size>2</size>
	</npc>
	<npc>
		<type>3558</type>
		<size>2</size>
	</npc>
	<npc>
		<type>3585</type>
		<size>2</size>
	</npc>
	<npc>
		<type>3586</type>
		<size>2</size>
	</npc>
	<npc>
		<type>3587</type>
		<size>2</size>
	</npc>
	<npc>
		<type>3588</type>
		<size>2</size>
	</npc>
	<npc>
		<type>3589</type>
		<size>3</size>
	</npc>
	<npc>
		<type>3590</type>
		<size>3</size>
	</npc>
	<npc>
		<type>3591</type>
		<size>3</size>
	</npc>
	<npc>
		<type>3592</type>
		<size>3</size>
	</npc>
	<npc>
		<type>3593</type>
		<size>3</size>
	</npc>
	<npc>
		<type>3594</type>
		<size>2</size>
	</npc>
	<npc>
		<type>3599</type>
		<size>3</size>
	</npc>
	<npc>
		<type>3600</type>
		<size>4</size>
	</npc>
	<npc>
		<type>3601</type>
		<size>5</size>
	</npc>
	<npc>
		<type>3602</type>
		<size>3</size>
	</npc>
	<npc>
		<type>3603</type>
		<size>3</size>
	</npc>
	<npc>
		<type>3604</type>
		<size>4</size>
	</npc>
	<npc>
		<type>3605</type>
		<size>5</size>
	</npc>
	<npc>
		<type>3606</type>
		<size>2</size>
	</npc>
	<npc>
		<type>3607</type>
		<size>2</size>
	</npc>
	<npc>
		<type>3608</type>
		<size>2</size>
	</npc>
	<npc>
		<type>3609</type>
		<size>2</size>
	</npc>
	<npc>
		<type>3610</type>
		<size>2</size>
	</npc>
	<npc>
		<type>3611</type>
		<size>2</size>
	</npc>
	<npc>
		<type>3612</type>
		<size>3</size>
	</npc>
	<npc>
		<type>3613</type>
		<size>3</size>
	</npc>
	<npc>
		<type>3614</type>
		<size>3</size>
	</npc>
	<npc>
		<type>3636</type>
		<size>2</size>
	</npc>
	<npc>
		<type>3637</type>
		<size>4</size>
	</npc>
	<npc>
		<type>3645</type>
		<size>2</size>
	</npc>
	<npc>
		<type>3646</type>
		<size>2</size>
	</npc>
	<npc>
		<type>3647</type>
		<size>2</size>
	</npc>
	<npc>
		<type>3649</type>
		<size>2</size>
	</npc>
	<npc>
		<type>3650</type>
		<size>2</size>
	</npc>
	<npc>
		<type>3651</type>
		<size>2</size>
	</npc>
	<npc>
		<type>3652</type>
		<size>2</size>
	</npc>
	<npc>
		<type>3653</type>
		<size>2</size>
	</npc>
	<npc>
		<type>3654</type>
		<size>2</size>
	</npc>
	<npc>
		<type>3655</type>
		<size>2</size>
	</npc>
	<npc>
		<type>3656</type>
		<size>2</size>
	</npc>
	<npc>
		<type>3657</type>
		<size>2</size>
	</npc>
	<npc>
		<type>3658</type>
		<size>3</size>
	</npc>
	<npc>
		<type>3659</type>
		<size>3</size>
	</npc>
	<npc>
		<type>3660</type>
		<size>3</size>
	</npc>
	<npc>
		<type>3661</type>
		<size>2</size>
	</npc>
	<npc>
		<type>3662</type>
		<size>2</size>
	</npc>
	<npc>
		<type>3664</type>
		<size>2</size>
	</npc>
	<npc>
		<type>3665</type>
		<size>2</size>
	</npc>
	<npc>
		<type>3666</type>
		<size>2</size>
	</npc>
	<npc>
		<type>3667</type>
		<size>2</size>
	</npc>
	<npc>
		<type>3668</type>
		<size>2</size>
	</npc>
	<npc>
		<type>3669</type>
		<size>2</size>
	</npc>
	<npc>
		<type>3670</type>
		<size>2</size>
	</npc>
	<npc>
		<type>3675</type>
		<size>2</size>
	</npc>
	<npc>
		<type>3676</type>
		<size>2</size>
	</npc>
	<npc>
		<type>3681</type>
		<size>3</size>
	</npc>
	<npc>
		<type>3772</type>
		<size>2</size>
	</npc>
	<npc>
		<type>3773</type>
		<size>2</size>
	</npc>
	<npc>
		<type>3774</type>
		<size>2</size>
	</npc>
	<npc>
		<type>3775</type>
		<size>2</size>
	</npc>
	<npc>
		<type>3776</type>
		<size>2</size>
	</npc>
	<npc>
		<type>3777</type>
		<size>3</size>
	</npc>
	<npc>
		<type>3778</type>
		<size>3</size>
	</npc>
	<npc>
		<type>3779</type>
		<size>3</size>
	</npc>
	<npc>
		<type>3780</type>
		<size>3</size>
	</npc>
	<npc>
		<type>3808</type>
		<size>3</size>
	</npc>
	<npc>
		<type>3819</type>
		<size>3</size>
	</npc>
	<npc>
		<type>3835</type>
		<size>5</size>
	</npc>
	<npc>
		<type>3836</type>
		<size>5</size>
	</npc>
</list>